{"otherData": {},"traceEvents":[{"cat":"function","dur":104802,"name":"glfwInit","ph":"X","pid":0,"tid":1528824210,"ts":144073458623},{"cat":"function","dur":628092,"name":"glfwCreateWindow","ph":"X","pid":0,"tid":1528824210,"ts":144073563631},{"cat":"function","dur":6536,"name":"void __cdecl Hazel::OpenGLContext::Init(void)","ph":"X","pid":0,"tid":1528824210,"ts":144074191889},{"cat":"function","dur":740039,"name":"void __cdecl Hazel::WindowsWindow::Init(const struct Hazel::WindowProps &)","ph":"X","pid":0,"tid":1528824210,"ts":144073458623},{"cat":"function","dur":52,"name":"__cdecl Hazel::OpenGLVertexArray::OpenGLVertexArray(void)","ph":"X","pid":0,"tid":1528824210,"ts":144074198799},{"cat":"function","dur":35,"name":"__cdecl Hazel::OpenGLVertexBuffer::OpenGLVertexBuffer(unsigned int)","ph":"X","pid":0,"tid":1528824210,"ts":144074198972},{"cat":"function","dur":0,"name":"void __cdecl Hazel::OpenGLVertexBuffer::Bind(void) const","ph":"X","pid":0,"tid":1528824210,"ts":144074199140},{"cat":"function","dur":841,"name":"__cdecl Hazel::OpenGLTexture2D::OpenGLTexture2D(unsigned int,unsigned int)","ph":"X","pid":0,"tid":1528824210,"ts":144074200543},{"cat":"function","dur":14,"name":"void __cdecl Hazel::OpenGLTexture2D::SetData(void *,unsigned int)","ph":"X","pid":0,"tid":1528824210,"ts":144074201568},{"cat":"function","dur":432,"name":"class std::basic_string<char,struct std::char_traits<char>,class std::allocator<char> > __cdecl Hazel::OpenGLShader::ReadFile(class std::basic_string_view<char,struct std::char_traits<char> >)","ph":"X","pid":0,"tid":1528824210,"ts":144074201681},{"cat":"function","dur":63,"name":"class std::unordered_map<unsigned int,class std::basic_string<char,struct std::char_traits<char>,class std::allocator<char> >,struct std::hash<unsigned int>,struct std::equal_to<unsigned int>,class std::allocator<struct std::pair<unsigned int const ,class std::basic_string<char,struct std::char_traits<char>,class std::allocator<char> > > > > __cdecl Hazel::OpenGLShader::PreProcess(const class std::basic_string<char,struct std::char_traits<char>,class std::allocator<char> > &)","ph":"X","pid":0,"tid":1528824210,"ts":144074202184},{"cat":"function","dur":1286,"name":"void __cdecl Hazel::OpenGLShader::Compile(const class std::unordered_map<unsigned int,class std::basic_string<char,struct std::char_traits<char>,class std::allocator<char> >,struct std::hash<unsigned int>,struct std::equal_to<unsigned int>,class std::allocator<struct std::pair<unsigned int const ,class std::basic_string<char,struct std::char_traits<char>,class std::allocator<char> > > > > &)","ph":"X","pid":0,"tid":1528824210,"ts":144074202323},{"cat":"function","dur":2062,"name":"__cdecl Hazel::OpenGLShader::OpenGLShader(class std::basic_string_view<char,struct std::char_traits<char> >)","ph":"X","pid":0,"tid":1528824210,"ts":144074201680},{"cat":"function","dur":6,"name":"void __cdecl Hazel::OpenGLShader::Bind(void) const","ph":"X","pid":0,"tid":1528824210,"ts":144074203834},{"cat":"function","dur":5258,"name":"void __cdecl Hazel::Renderer2D::Init(void)","ph":"X","pid":0,"tid":1528824210,"ts":144074198782},{"cat":"function","dur":5340,"name":"void __cdecl Hazel::Renderer::Init(void)","ph":"X","pid":0,"tid":1528824210,"ts":144074198771},{"cat":"function","dur":747536,"name":"__cdecl Hazel::Application::Application(const class std::basic_string<char,struct std::char_traits<char>,class std::allocator<char> > &)","ph":"X","pid":0,"tid":1528824210,"ts":144073458601},{"cat":"function","dur":5256,"name":"OpenGLTexture2D::OpenGLTexture2D(const std::string&)::stbi_load","ph":"X","pid":0,"tid":1528824210,"ts":144074207078},{"cat":"function","dur":5585,"name":"__cdecl Hazel::OpenGLTexture2D::OpenGLTexture2D(const class std::basic_string<char,struct std::char_traits<char>,class std::allocator<char> > &)","ph":"X","pid":0,"tid":1528824210,"ts":144074207077},{"cat":"function","dur":218169,"name":"OpenGLTexture2D::OpenGLTexture2D(const std::string&)::stbi_load","ph":"X","pid":0,"tid":1528824210,"ts":144074212742},{"cat":"function","dur":229426,"name":"__cdecl Hazel::OpenGLTexture2D::OpenGLTexture2D(const class std::basic_string<char,struct std::char_traits<char>,class std::allocator<char> > &)","ph":"X","pid":0,"tid":1528824210,"ts":144074212742},{"cat":"function","dur":4,"name":"void __cdecl Hazel::OrthographicCamera::SetProjection(float,float,float,float)","ph":"X","pid":0,"tid":1528824210,"ts":144074445121}]}